pants_backend_kustomize/__init__.py
pants_backend_kustomize/codegen.py
pants_backend_kustomize/goals/tailor.py
pants_backend_kustomize/register.py
pants_backend_kustomize/requests.py
pants_backend_kustomize/subsystem.py
pants_backend_kustomize/target_types.py
pants_backend_kustomize/util_rules/prepare_context.py
pants_backend_kustomize-0.5.0.dist-info/WHEEL
pants_backend_kustomize-0.5.0.dist-info/METADATA
pants_backend_kustomize-0.5.0.dist-info/licenses/LICENSE-MIT.txt
pants_backend_kustomize-0.5.0.dist-info/RECORD
