Metadata-Version: 2.1
Name: pants_backend_kustomize
Version: 0.5.0
Summary: A Kustomize plugin for the Pants build system
Keywords: pantsbuild,pants,backend,kustomize,kubernetes
Author-email: Tom Solberg <me@sbg.dev>
Classifier: Development Status :: 4 - Beta
Classifier: Programming Language :: Python
Classifier: Topic :: Software Development :: Build Tools
Requires-Dist: pants_backend_k8s>=0.4
Project-URL: Changelog, https://github.com/tgolsson/pants-backends/tree/main/pants-plugins/kustomize/CHANGELOG.md
Project-URL: Code, https://github.com/tgolsson/pants-backends/tree/main/pants-plugins/kustomize
Project-URL: Repository, https://github.com/tgolsson/pants-backends
